test/__init__.py
test/schema_test_helper.py
test/test_active_connectors.py
test/test_app_block_events.py
test/test_app_logger.py
test/test_async_app_run.py
test/test_config_loader.py
test/test_config_loader_helper.py
test/test_config_model.py
test/test_config_model_solar_pants.py
test/test_data_cache.py
test/test_data_checker.py
test/test_loader.py
test/test_redis_api.py
test/test_redis_cache.py
test/test_redis_h_time_series.py
test/test_redis_worker.py
test/test_schema_app_blocks.py
test/test_schema_app_connectors.py
test/test_schema_battery_bank.py
test/test_schema_data_structure.py
test/test_schema_emoncms.py
test/test_schema_imports.py
test/test_schema_validate.py
test/test_schema_validate_selector.py
test/test_threads_controller.py
test/test_utils.py
test/test_vedirect_app.py
test/test_yaml_loader.py
test/vedirectsim.py
test/conf/appBlocksTest.yaml
test/conf/appConnectorsTest.yaml
test/conf/batteryBankArgsTest.yaml
test/conf/batteryBanksTest.yaml
test/conf/dummy_conf_dict.yaml
test/conf/dummy_conf_dict1.yaml
test/conf/dummy_conf_dict2.yaml
test/conf/dummy_conf_dict_bad_imports.yaml
test/conf/dummy_conf_dict_error.yaml
test/conf/dummy_conf_list.yaml
test/conf/dummy_conf_list1.yaml
test/conf/dummy_conf_list2.yaml
test/conf/dummy_conf_list_bad_imports.yaml
test/conf/dummy_emoncms.yaml
test/conf/dummy_g_appConnectors.yaml
test/conf/dummy_g_batteryBank.yaml
test/conf/dummy_g_conf.yaml
test/conf/emoncmsTest.yaml
test/conf/empty.yaml
test/conf/import_bad_ext.yaml
test/conf/import_empty.yaml
test/conf/import_not_found.yaml
vemonitor_m8/__init__.py
vemonitor_m8/app_run.py
vemonitor_m8/version.py
vemonitor_m8/conf_manager/__init__.py
vemonitor_m8/conf_manager/loader.py
vemonitor_m8/conf_manager/schema_validate.py
vemonitor_m8/conf_manager/confFiles/victronDeviceData.yaml
vemonitor_m8/core/__init__.py
vemonitor_m8/core/exceptions.py
vemonitor_m8/core/utils.py
vemonitor_m8/models/__init__.py
vemonitor_m8/models/item_dict.py
vemonitor_m8/models/workers.py
vemonitor_m8-0.1.2.dist-info/LICENSE
vemonitor_m8-0.1.2.dist-info/METADATA
vemonitor_m8-0.1.2.dist-info/WHEEL
vemonitor_m8-0.1.2.dist-info/top_level.txt
vemonitor_m8-0.1.2.dist-info/RECORD
