Metadata-Version: 2.1
Name: vemonitor_m8
Version: 0.1.2
Summary: Solar Plant Monitoring
Home-page: https://github.com/vemonitor/vemonitor_m8
Author: Eli Serra
Author-email: eli.serra173@gmail.com
License: Apache
Classifier: License :: OSI Approved :: Apache Software License
Classifier: Programming Language :: Python :: 3
Classifier: Programming Language :: Python :: 3.7
Classifier: Programming Language :: Python :: 3.8
Classifier: Programming Language :: Python :: 3.9
Classifier: Programming Language :: Python :: 3.10
Classifier: Programming Language :: Python :: 3.11
Requires-Python: >3.5.2
License-File: LICENSE
Requires-Dist: jsonschema >=4.23.0
Requires-Dist: pyyaml >=6.0.2
Requires-Dist: simplejson >=3.19.2
Requires-Dist: redis >=5.0.8
Requires-Dist: vedirect-m8 >=1.3.4
Requires-Dist: ve-utils >=2.5.3
Provides-Extra: test
Requires-Dist: pytest >=8.3.2 ; extra == 'test'
Requires-Dist: pytest-cov >=5.0.0 ; extra == 'test'
Requires-Dist: coverage >=7.6.1 ; extra == 'test'
Requires-Dist: setuptools >=72.1.0 ; extra == 'test'
Requires-Dist: twine >=5.1.1 ; extra == 'test'
Requires-Dist: wheel >=0.44.0 ; extra == 'test'
Requires-Dist: flake8 >=7.1.1 ; extra == 'test'
